plaquette_ibm_backend/__init__.py
plaquette_ibm_backend/__main__.py
plaquette_ibm_backend/backend.py
plaquette_ibm_backend-0.0.2.post0.dist-info/LICENSE
plaquette_ibm_backend-0.0.2.post0.dist-info/METADATA
plaquette_ibm_backend-0.0.2.post0.dist-info/WHEEL
plaquette_ibm_backend-0.0.2.post0.dist-info/entry_points.txt
plaquette_ibm_backend-0.0.2.post0.dist-info/top_level.txt
plaquette_ibm_backend-0.0.2.post0.dist-info/RECORD
