Metadata-Version: 2.1
Name: plaquette-ibm-backend
Version: 0.0.2.post0
Summary: Plugin connecting plaquette to the IBM Quantum Systems and Simulators
Author-email: QC Design GmbH <software@qc.design>
Project-URL: Homepage, https://docs.plaquette.design/projects/ibm-backend
Project-URL: Bug Tracker, https://github.com/qc-design/plaquette-ibm-backend/issues
Keywords: Quantum error correction
Classifier: Development Status :: 3 - Alpha
Classifier: Intended Audience :: Developers
Classifier: Natural Language :: English
Classifier: Programming Language :: Python :: 3
Classifier: Programming Language :: Python :: 3.10
Requires-Python: >=3.10
License-File: LICENSE
Requires-Dist: qiskit
Requires-Dist: qiskit-ibm-provider
Requires-Dist: plaquette >=0.0.1a3
